<annotation>
	<folder>n02876657</folder>
	<filename>n02876657_7319</filename>
	<source>
		<database>ImageNet database</database>
	</source>
	<size>
		<width>500</width>
		<height>496</height>
		<depth>3</depth>
	</size>
	<segmented>0</segmented>
	<object>
		<name>n02876657</name>
		<pose>Unspecified</pose>
		<truncated>0</truncated>
		<difficult>0</difficult>
		<bndbox>
			<xmin>43</xmin>
			<ymin>135</ymin>
			<xmax>346</xmax>
			<ymax>411</ymax>
		</bndbox>
	</object>
	<object>
		<name>n02876657</name>
		<pose>Unspecified</pose>
		<truncated>0</truncated>
		<difficult>0</difficult>
		<bndbox>
			<xmin>47</xmin>
			<ymin>135</ymin>
			<xmax>362</xmax>
			<ymax>415</ymax>
		</bndbox>
	</object>
</annotation>